Detection/__init__.py
image_annotation-0.3.3.dist-info/METADATA
image_annotation-0.3.3.dist-info/WHEEL
image_annotation-0.3.3.dist-info/top_level.txt
image_annotation-0.3.3.dist-info/RECORD
