Metadata-Version: 2.1
Name: image_annotation
Version: 0.3.3
Summary: streamlit components for image annotation, with customization
Home-page: https://github.com/hoc1190/image_annotation
Author: hirune924
Keywords: Python,Streamlit,React,JavaScript
Requires-Python: >=3.6
Requires-Dist: streamlit >=0.63
